{
  "kind": "singleType",
  "collectionName": "vision_pages",
  "info": {
    "singularName": "vision-page",
    "pluralName": "vision-pages",
    "displayName": "Vision page"
  },
  "options": {
    "draftAndPublish": false
  },
  "pluginOptions": {
    "i18n": {
      "localized": true
    }
  },
  "attributes": {
    "vision": {
      "pluginOptions": {
        "i18n": {
          "localized": true
        },
        "translate": {
          "translate": "translate"
        }
      },
      "type": "text",
      "required": true
    },
    "mission": {
      "pluginOptions": {
        "i18n": {
          "localized": true
        },
        "translate": {
          "translate": "translate"
        }
      },
      "type": "text",
      "required": true
    },
    "core_values": {
      "type": "component",
      "repeatable": true,
      "pluginOptions": {
        "i18n": {
          "localized": true
        },
        "translate": {
          "translate": "translate"
        }
      },
      "component": "about.value"
    },
    "objectives": {
      "type": "component",
      "repeatable": true,
      "pluginOptions": {
        "i18n": {
          "localized": true
        },
        "translate": {
          "translate": "translate"
        }
      },
      "component": "about.name-card"
    }
  }
}
